{
  "name": "Employee",
  "fields": [
    {
      "fieldName": "name",
      "fieldType": "String",
      "fieldValidateRules": ["required"]
    },
    {
      "fieldName": "department",
      "fieldType": "String",
      "fieldValidateRules": ["required"]
    },
    {
      "fieldName": "salary",
      "fieldType": "Double"
    }
  ],
  "relationships": [],
  "entityTableName": "employee",
  "dto": "no",
  "pagination": "no",
  "service": "no",
  "jpaMetamodelFiltering": false,
  "fluentMethods": true,
  "readOnly": false,
  "embedded": false,
  "applications": ["myApp"],
  "changelogDate": "20210405192902"
}
